LICENCEC.txt
MANIFEST.in
README.MD
setup.py
python_helpers/__init__.py
python_helpers.egg-info/SOURCES.txt
python_helpers.egg-info/dependency_links.txt
python_helpers.egg-info/requires.txt
python_helpers.egg-info/top_level.txt
pythons_helpers.egg-info/PKG-INFO
pythons_helpers.egg-info/SOURCES.txt
pythons_helpers.egg-info/dependency_links.txt
pythons_helpers.egg-info/requires.txt
pythons_helpers.egg-info/top_level.txt