Metadata-Version: 2.1
Name: pythons-helpers
Version: 0.1.0
Summary: A collection of helpful python functions
Home-page: UNKNOWN
Author: 8au
License: MIT
Keywords: python helpers,python3 helpers,pythonhelpers,helperfunctions,helperfunctionspython,helperfunctionspython3
Platform: UNKNOWN
License-File: LICENCEC.txt
